asterAI/__init__.py
asterAI/facenet.py
asterAI-0.1.1.dist-info/METADATA
asterAI-0.1.1.dist-info/WHEEL
asterAI-0.1.1.dist-info/top_level.txt
asterAI-0.1.1.dist-info/RECORD
