Metadata-Version: 2.1
Name: asterAI
Version: 0.1.1
Requires-Dist: facenet-pytorch (>=2.5.3)
Requires-Dist: Pillow (==10.1.0)
Requires-Dist: faiss-cpu (==1.8.0)
Requires-Dist: numpy (==1.26.2)
